LICENSE
MANIFEST.in
README.md
pyproject.toml
requirements.txt
setup.py
OpenCTM-1.0.3/COMPILING.txt
OpenCTM-1.0.3/LICENSE.txt
OpenCTM-1.0.3/Makefile.linux
OpenCTM-1.0.3/Makefile.macosx
OpenCTM-1.0.3/Makefile.mingw
OpenCTM-1.0.3/Makefile.msvc
OpenCTM-1.0.3/README.txt
OpenCTM-1.0.3/lib/Makefile.linux
OpenCTM-1.0.3/lib/Makefile.macosx
OpenCTM-1.0.3/lib/Makefile.mingw
OpenCTM-1.0.3/lib/Makefile.msvc
OpenCTM-1.0.3/lib/compressMG1.c
OpenCTM-1.0.3/lib/compressMG2.c
OpenCTM-1.0.3/lib/compressRAW.c
OpenCTM-1.0.3/lib/internal.h
OpenCTM-1.0.3/lib/libopenctm.a
OpenCTM-1.0.3/lib/openctm-mingw1.def
OpenCTM-1.0.3/lib/openctm-mingw2.def
OpenCTM-1.0.3/lib/openctm-msvc.def
OpenCTM-1.0.3/lib/openctm.c
OpenCTM-1.0.3/lib/openctm.h
OpenCTM-1.0.3/lib/openctm.rc
OpenCTM-1.0.3/lib/openctmpp.h
OpenCTM-1.0.3/lib/stream.c
OpenCTM-1.0.3/lib/liblzma/Alloc.c
OpenCTM-1.0.3/lib/liblzma/Alloc.h
OpenCTM-1.0.3/lib/liblzma/LzFind.c
OpenCTM-1.0.3/lib/liblzma/LzFind.h
OpenCTM-1.0.3/lib/liblzma/LzHash.h
OpenCTM-1.0.3/lib/liblzma/LzmaDec.c
OpenCTM-1.0.3/lib/liblzma/LzmaDec.h
OpenCTM-1.0.3/lib/liblzma/LzmaEnc.c
OpenCTM-1.0.3/lib/liblzma/LzmaEnc.h
OpenCTM-1.0.3/lib/liblzma/LzmaLib.c
OpenCTM-1.0.3/lib/liblzma/LzmaLib.h
OpenCTM-1.0.3/lib/liblzma/NameMangle.h
OpenCTM-1.0.3/lib/liblzma/Types.h
OpenCTM-1.0.3/lib/liblzma/readme.txt
cortex/__init__.py
cortex/align.py
cortex/anat.py
cortex/appdirs.py
cortex/bbr.sch
cortex/brainctm.py
cortex/database.py
cortex/defaults.cfg
cortex/fmriprep.py
cortex/formats.c
cortex/formats.pyx
cortex/formats_old.py
cortex/freesurfer.py
cortex/mayavi_aligner.py
cortex/mni.py
cortex/mp.py
cortex/openctm.c
cortex/openctm.pxd
cortex/openctm.pyx
cortex/options.py
cortex/rois.py
cortex/segment.py
cortex/surfinfo.py
cortex/svgbase.xml
cortex/svgoverlay.py
cortex/testing_utils.py
cortex/utils.py
cortex/version.py
cortex/volume.py
cortex/xfm.py
cortex/blender/__init__.py
cortex/blender/blendlib.py
cortex/dataset/__init__.py
cortex/dataset/braindata.py
cortex/dataset/dataset.py
pycortex.egg-info/PKG-INFO
pycortex.egg-info/SOURCES.txt
pycortex.egg-info/dependency_links.txt
pycortex.egg-info/requires.txt
pycortex.egg-info/top_level.txt