Metadata-Version: 2.4
Name: pycortex
Version: 1.2.12
Summary: Python Cortical mapping software for fMRI data
Home-page: http://gallantlab.github.io/pycortex
Download-URL: http://gallantlab.github.io/pycortex
Author: James Gao
Author-email: james@jamesgao.com
License: 2-clause BSD license
Classifier: Development Status :: 6 - Mature
Classifier: Intended Audience :: Science/Research
Classifier: License :: OSI Approved :: BSD License
Classifier: Operating System :: OS Independent
Classifier: Programming Language :: Python
Classifier: Programming Language :: Python :: Implementation :: CPython
Classifier: Topic :: Scientific/Engineering :: Visualization
License-File: LICENSE
Requires-Dist: setuptools
Requires-Dist: future
Requires-Dist: numpy
Requires-Dist: scipy
Requires-Dist: tornado>=4.3
Requires-Dist: shapely
Requires-Dist: lxml
Requires-Dist: html5lib
Requires-Dist: h5py
Requires-Dist: numexpr
Requires-Dist: cython
Requires-Dist: matplotlib
Requires-Dist: pillow
Requires-Dist: nibabel>=2.1
Requires-Dist: networkx>=2.1
Requires-Dist: imageio
Requires-Dist: looseversion
Requires-Dist: mda_xdrlib
Dynamic: author
Dynamic: author-email
Dynamic: classifier
Dynamic: description
Dynamic: description-content-type
Dynamic: download-url
Dynamic: home-page
Dynamic: license
Dynamic: license-file
Dynamic: requires-dist
Dynamic: summary
